{
  "_doc": "Pesquisas presidenciais 2026 - LEITURA B: soma esquerda (Lula+Haddad+...) vs soma direita (Flavio+Caiado+Zema+Renan+...). Captura cenario do 2T onde a direita unifica.",
  "_metodologia": "Bloco esquerda = Lula (e outros eventuais). Bloco direita = Flavio Bolsonaro + Caiado + Zema + Renan Santos (Missao). Cenario 1T com Flavio como candidato principal direita.",
  "_fonte": "Wikipedia - Pesquisas de opiniao para a eleicao presidencial no Brasil em 2026, atualizada em 31/maio/2026",
  "_url_fonte": "https://pt.wikipedia.org/wiki/Pesquisas_de_opini%C3%A3o_para_a_elei%C3%A7%C3%A3o_presidencial_no_Brasil_em_2026",
  "pesquisas": [
    {
      "instituto": "Real Time Big Data",
      "data": "2026-05-30",
      "esquerda_pct": 38.0,
      "direita_pct": 48.0,
      "indecisos_brancos": 8.0,
      "cenario": "Lula 38 | Flavio 31 + Caiado 6 + Zema 5 + Renan 6",
      "n_entrevistas": 2000
    },
    {
      "instituto": "PoderData/AYA",
      "data": "2026-05-28",
      "esquerda_pct": 40.0,
      "direita_pct": 45.0,
      "indecisos_brancos": 9.0,
      "cenario": "Lula 40 | Flavio 35 + Caiado 3 + Zema 4 + Renan 3",
      "n_entrevistas": 2400
    },
    {
      "instituto": "Meio/Ideia",
      "data": "2026-05-27",
      "esquerda_pct": 38.5,
      "direita_pct": 41.5,
      "indecisos_brancos": 15.6,
      "cenario": "Lula 38.5 | Flavio 31.5 + Caiado 5.5 + Zema 2.4 + Renan 2.1",
      "n_entrevistas": 1500
    },
    {
      "instituto": "Indexa",
      "data": "2026-05-24",
      "esquerda_pct": 39.0,
      "direita_pct": 45.0,
      "indecisos_brancos": 18.0,
      "cenario": "Lula 39 | Flavio 30 + Caiado 5 + Zema 5 + Renan 5",
      "n_entrevistas": 2000
    },
    {
      "instituto": "Nexus/BTG",
      "data": "2026-05-24",
      "esquerda_pct": 41.0,
      "direita_pct": 48.0,
      "indecisos_brancos": 8.0,
      "cenario": "Lula 41 | Flavio 35 + Caiado 5 + Zema 4 + Renan 4",
      "n_entrevistas": 2045
    },
    {
      "instituto": "Datafolha",
      "data": "2026-05-21",
      "esquerda_pct": 40.0,
      "direita_pct": 39.0,
      "indecisos_brancos": 12.0,
      "cenario": "Lula 40 | Flavio 31 + Caiado 4 + Zema 3 + Renan 1",
      "n_entrevistas": 2004
    },
    {
      "instituto": "Gerp",
      "data": "2026-05-21",
      "esquerda_pct": 38.0,
      "direita_pct": 46.0,
      "indecisos_brancos": 10.0,
      "cenario": "Lula 38 | Flavio 38 + Caiado 2 + Zema 3 + Renan 3",
      "n_entrevistas": 2000
    },
    {
      "instituto": "Apex/Futura",
      "data": "2026-05-20",
      "esquerda_pct": 42.7,
      "direita_pct": 44.5,
      "indecisos_brancos": 10.6,
      "cenario": "Lula 42.7 | Flavio 35.6 + Caiado 3.3 + Zema 3.9 + Renan 1.7",
      "n_entrevistas": 2000
    },
    {
      "instituto": "Vox Brasil",
      "data": "2026-05-19",
      "esquerda_pct": 41.5,
      "direita_pct": 43.6,
      "indecisos_brancos": 14.3,
      "cenario": "Lula 41.5 | Flavio 32.1 + Caiado 5.9 + Zema 4.1 + Renan 1.5",
      "n_entrevistas": 2100
    },
    {
      "instituto": "Vetor/Arrow",
      "data": "2026-05-18",
      "esquerda_pct": 37.4,
      "direita_pct": 44.1,
      "indecisos_brancos": 15.8,
      "cenario": "Lula 37.4 | Flavio 30.2 + Caiado 2.9 + Zema 3.6 + Renan 7.4",
      "n_entrevistas": 9000
    },
    {
      "instituto": "AtlasIntel",
      "data": "2026-05-18",
      "esquerda_pct": 47.0,
      "direita_pct": 49.1,
      "indecisos_brancos": 3.3,
      "cenario": "Lula 47 | Flavio 34.3 + Caiado 2.7 + Zema 5.2 + Renan 6.9",
      "n_entrevistas": 5032
    },
    {
      "instituto": "Verita",
      "data": "2026-05-15",
      "esquerda_pct": 37.2,
      "direita_pct": 48.7,
      "indecisos_brancos": 11.5,
      "cenario": "Lula 37.2 | Flavio 37.0 + Caiado 2.9 + Zema 6.5 + Renan 2.3",
      "n_entrevistas": 3404
    }
  ]
}
